ptm/__init__.py
ptm/ptm_settings.py
ptm/results.py
ptm/actions/__init__.py
ptm/actions/path_actions.py
ptm/actions/result_actions.py
ptm/adventure_managment/__init__.py
ptm/adventure_managment/spells/__init__.py
ptm/adventure_managment/spells/recipe.py
ptm/adventure_managment/spells/types.py
ptm/adventure_managment/spells/implementations/__init__.py
ptm/adventure_managment/spells/implementations/create_land.py
ptm/adventure_managment/spells/implementations/create_travel.py
ptm/adventure_managment/spells/implementations/run_adventure.py
ptm/adventure_managment/spells/implementations/start_adventure.py
ptm/adventure_managment/spells/implementations/utils.py
ptm/templates/travel_template.py
ptm/templates/adventure_template/gendalf.py
ptm/templates/adventure_template/rucksack.py
ptm/templates/adventure_template/extensions/__init__.py
ptm/templates/adventure_template/smithy/__init__.py
ptm/templates/adventure_template/travels/__init__.py
ptm/templates/adventure_template/treasy/__init__.py
ptm-0.0.1a4.dist-info/DESCRIPTION.rst
ptm-0.0.1a4.dist-info/METADATA
ptm-0.0.1a4.dist-info/RECORD
ptm-0.0.1a4.dist-info/WHEEL
ptm-0.0.1a4.dist-info/entry_points.txt
ptm-0.0.1a4.dist-info/metadata.json
ptm-0.0.1a4.dist-info/top_level.txt
