Metadata-Version: 2.0
Name: ptm
Version: 0.0.1a4
Summary: UNKNOWN
Home-page: https://github.com/acrius/path_to_mordor
Author: acrius
Author-email: acrius@mail.ru
License: MIT
Platform: UNKNOWN
Requires-Dist: beautifulsoup4
